{
  "schemaVersion": 1,
  "id": "rswires",
  "version": "${version}",
  "name": "RSWires",
  "description": "Improved redstone, or something.",
  "authors": [
    "2xsaiko"
  ],
  "contact": {
    "homepage": "https://github.com/2xsaiko/HCTM",
    "sources": "https://github.com/2xsaiko/HCTM"
  },
  "license": "MIT",
  "icon": "assets/rswires/icon.png",
  "environment": "*",
  "entrypoints": {
    "main": [{ "value": "net.dblsaiko.rswires.RSWires", "adapter": "kotlin" }],
    "client": [{ "value": "net.dblsaiko.rswires.client.RSWiresClient", "adapter": "kotlin" }]
  },
  "depends": {
    "minecraft": "~1.17",
    "fabricloader": ">=0.4.0",
    "fabric": "*",
    "fabric-language-kotlin": ">=1.4",
    "hctm-base": "^3.5.0",
    "libaddict": ">=0.3.0"
  },
  "suggests": {
    "retrocomputers": ">=4.0.0"
  }
}